cssminifier
