Metadata-Version: 2.1
Name: cssminifier
Version: 0.0.3
Summary: Minification tool for Cascading Style Sheets (CSS)
Home-page: https://github.com/qyful/cssminifier
Download-URL: https://github.com/qyful/CSSMinifier/archive/refs/tags/v0.0.1.tar.gz
Author: Oliwier Sporny
Author-email: me@oliwiersporny.com
License: MIT
Keywords: css,css3,minifier,minification,minify,minify-css
Classifier: Development Status :: 4 - Beta
Classifier: Intended Audience :: Education
Classifier: Programming Language :: Python :: 2
Classifier: Programming Language :: Python :: 3
Classifier: Operating System :: MacOS :: MacOS X
Classifier: Operating System :: Microsoft :: Windows
License-File: LICENSE
